azEnvJson/__init__.py
azEnvJson/convert.py
azEnvJson/read.py
azenvjson-0.2.0.dist-info/METADATA
azenvjson-0.2.0.dist-info/WHEEL
azenvjson-0.2.0.dist-info/RECORD
